dorasl/__init__.py
dorasl/__test.py
dorasl/dora.py
dorasl/dorasl.py
dorasl-0.1.7.dist-info/METADATA
dorasl-0.1.7.dist-info/WHEEL
dorasl-0.1.7.dist-info/top_level.txt
dorasl-0.1.7.dist-info/RECORD
