Metadata-Version: 2.1
Name: dorasl
Version: 0.1.7
Summary: UNKNOWN
Home-page: UNKNOWN
Author: Amedeo Setti
Author-email: amedeosetti@gmail.com
License: MIT
Platform: UNKNOWN
